{"mayor":"Bill de Blasio","commissioner":"William J. Bratton","volume":21,"number":34,"precinct":"Patrol BoroughManhattan North","startDate":"2014-08-18T04:00:00.000Z","endDate":"2014-08-24T04:00:00.000Z","crimes":[{"crime":"Murder","wtd_curr_yr":1,"wtd_prev_yr":0,"wtd_pct_change":null,"twentyeight_day_curr_yr":7,"twentyeight_day_prev_yr":2,"twentyeight_day_pct_change":250,"ytd_curr_yr":19,"ytd_prev_yr":15,"ytd_pct_change":26.7,"two_year_pct_change":-45.7,"six_year_pct_change":-32.1,"twentytwo_year_pct_change":-91.4},{"crime":"Rape","wtd_curr_yr":7,"wtd_prev_yr":4,"wtd_pct_change":75,"twentyeight_day_curr_yr":19,"twentyeight_day_prev_yr":10,"twentyeight_day_pct_change":90,"ytd_curr_yr":122,"ytd_prev_yr":124,"ytd_pct_change":-1.6,"two_year_pct_change":-13.5,"six_year_pct_change":32.6,"twentytwo_year_pct_change":-62.8},{"crime":"Robbery","wtd_curr_yr":44,"wtd_prev_yr":51,"wtd_pct_change":-13.7,"twentyeight_day_curr_yr":159,"twentyeight_day_prev_yr":185,"twentyeight_day_pct_change":-14.1,"ytd_curr_yr":1163,"ytd_prev_yr":1338,"ytd_pct_change":-13.1,"two_year_pct_change":-17.8,"six_year_pct_change":-18.4,"twentytwo_year_pct_change":-81.1},{"crime":"Fel. Assault","wtd_curr_yr":50,"wtd_prev_yr":44,"wtd_pct_change":13.6,"twentyeight_day_curr_yr":165,"twentyeight_day_prev_yr":167,"twentyeight_day_pct_change":-1.2,"ytd_curr_yr":1327,"ytd_prev_yr":1372,"ytd_pct_change":-3.3,"two_year_pct_change":-4.1,"six_year_pct_change":7.3,"twentytwo_year_pct_change":-65.8},{"crime":"Burglary","wtd_curr_yr":24,"wtd_prev_yr":31,"wtd_pct_change":-22.6,"twentyeight_day_curr_yr":109,"twentyeight_day_prev_yr":127,"twentyeight_day_pct_change":-14.2,"ytd_curr_yr":830,"ytd_prev_yr":872,"ytd_pct_change":-4.8,"two_year_pct_change":-14.2,"six_year_pct_change":-10.8,"twentytwo_year_pct_change":-88.4},{"crime":"Gr. Larceny","wtd_curr_yr":116,"wtd_prev_yr":100,"wtd_pct_change":16,"twentyeight_day_curr_yr":435,"twentyeight_day_prev_yr":456,"twentyeight_day_pct_change":-4.6,"ytd_curr_yr":3354,"ytd_prev_yr":3525,"ytd_pct_change":-4.9,"two_year_pct_change":0.8,"six_year_pct_change":13.3,"twentytwo_year_pct_change":-52.7},{"crime":"G.L.A.","wtd_curr_yr":12,"wtd_prev_yr":12,"wtd_pct_change":0,"twentyeight_day_curr_yr":46,"twentyeight_day_prev_yr":51,"twentyeight_day_pct_change":-9.8,"ytd_curr_yr":283,"ytd_prev_yr":284,"ytd_pct_change":-0.4,"two_year_pct_change":-6,"six_year_pct_change":-33.7,"twentytwo_year_pct_change":-95.3},{"crime":"TOTAL","wtd_curr_yr":254,"wtd_prev_yr":242,"wtd_pct_change":4.96,"twentyeight_day_curr_yr":940,"twentyeight_day_prev_yr":998,"twentyeight_day_pct_change":-5.81,"ytd_curr_yr":7098,"ytd_prev_yr":7530,"ytd_pct_change":-5.74,"two_year_pct_change":-6.21,"six_year_pct_change":0,"twentytwo_year_pct_change":-77},{"crime":"Transit","wtd_curr_yr":6,"wtd_prev_yr":8,"wtd_pct_change":-25,"twentyeight_day_curr_yr":20,"twentyeight_day_prev_yr":26,"twentyeight_day_pct_change":-23.1,"ytd_curr_yr":167,"ytd_prev_yr":211,"ytd_pct_change":-20.9,"two_year_pct_change":-29.2,"six_year_pct_change":3.7,"twentytwo_year_pct_change":null},{"crime":"Housing","wtd_curr_yr":25,"wtd_prev_yr":23,"wtd_pct_change":8.7,"twentyeight_day_curr_yr":93,"twentyeight_day_prev_yr":82,"twentyeight_day_pct_change":13.4,"ytd_curr_yr":642,"ytd_prev_yr":631,"ytd_pct_change":1.7,"two_year_pct_change":0.8,"six_year_pct_change":23.9,"twentytwo_year_pct_change":null},{"crime":"Petit Larceny","wtd_curr_yr":216,"wtd_prev_yr":193,"wtd_pct_change":11.9,"twentyeight_day_curr_yr":869,"twentyeight_day_prev_yr":861,"twentyeight_day_pct_change":0.9,"ytd_curr_yr":6246,"ytd_prev_yr":6356,"ytd_pct_change":-1.7,"two_year_pct_change":-0.7,"six_year_pct_change":6.5,"twentytwo_year_pct_change":null},{"crime":"Misd. Assault","wtd_curr_yr":85,"wtd_prev_yr":77,"wtd_pct_change":10.4,"twentyeight_day_curr_yr":387,"twentyeight_day_prev_yr":379,"twentyeight_day_pct_change":2.1,"ytd_curr_yr":3179,"ytd_prev_yr":3192,"ytd_pct_change":-0.4,"two_year_pct_change":-4.9,"six_year_pct_change":-5.8,"twentytwo_year_pct_change":null},{"crime":"Misd. Sex Crimes","wtd_curr_yr":8,"wtd_prev_yr":4,"wtd_pct_change":100,"twentyeight_day_curr_yr":33,"twentyeight_day_prev_yr":25,"twentyeight_day_pct_change":32,"ytd_curr_yr":213,"ytd_prev_yr":189,"ytd_pct_change":12.7,"two_year_pct_change":-12,"six_year_pct_change":15.1,"twentytwo_year_pct_change":null},{"crime":"Shooting Vic.","wtd_curr_yr":3,"wtd_prev_yr":5,"wtd_pct_change":-40,"twentyeight_day_curr_yr":15,"twentyeight_day_prev_yr":17,"twentyeight_day_pct_change":-11.8,"ytd_curr_yr":76,"ytd_prev_yr":71,"ytd_pct_change":7,"two_year_pct_change":-38.2,"six_year_pct_change":-28.3,"twentytwo_year_pct_change":-85.5},{"crime":"Shooting Inc.","wtd_curr_yr":3,"wtd_prev_yr":4,"wtd_pct_change":-25,"twentyeight_day_curr_yr":12,"twentyeight_day_prev_yr":15,"twentyeight_day_pct_change":-20,"ytd_curr_yr":64,"ytd_prev_yr":61,"ytd_pct_change":4.9,"two_year_pct_change":-35.4,"six_year_pct_change":-21,"twentytwo_year_pct_change":-86.7}],"historical":[{"yr_1990":379,"yr_1993":306,"yr_1998":78,"yr_2001":78,"yr_2013":27,"pct_change_13vs01":-65.4,"pct_change_13vs98":-65.4,"pct_change_13vs93":-91.2,"pct_change_13vs90":-92.9,"crime":"Murder"},{"yr_1990":482,"yr_1993":510,"yr_1998":315,"yr_2001":226,"yr_2013":182,"pct_change_13vs01":-19.5,"pct_change_13vs98":-42.2,"pct_change_13vs93":-64.3,"pct_change_13vs90":-62.2,"crime":"Rape"},{"yr_1990":12041,"yr_1993":9730,"yr_1998":4603,"yr_2001":3343,"yr_2013":2151,"pct_change_13vs01":-35.7,"pct_change_13vs98":-53.3,"pct_change_13vs93":-77.9,"pct_change_13vs90":-82.1,"crime":"Robbery"},{"yr_1990":6092,"yr_1993":5796,"yr_1998":3824,"yr_2001":2911,"yr_2013":2051,"pct_change_13vs01":-29.5,"pct_change_13vs98":-46.4,"pct_change_13vs93":-64.6,"pct_change_13vs90":-66.3,"crime":"Fel. Assault"},{"yr_1990":14267,"yr_1993":11441,"yr_1998":4879,"yr_2001":2818,"yr_2013":1362,"pct_change_13vs01":-51.7,"pct_change_13vs98":-72.1,"pct_change_13vs93":-88.1,"pct_change_13vs90":-90.5,"crime":"Burglary"},{"yr_1990":13799,"yr_1993":11055,"yr_1998":5824,"yr_2001":5430,"yr_2013":5654,"pct_change_13vs01":4.1,"pct_change_13vs98":-2.9,"pct_change_13vs93":-48.9,"pct_change_13vs90":-59,"crime":"Gr. Larceny"},{"yr_1990":12028,"yr_1993":9418,"yr_1998":3143,"yr_2001":1997,"yr_2013":433,"pct_change_13vs01":-78.3,"pct_change_13vs98":-86.2,"pct_change_13vs93":-95.4,"pct_change_13vs90":-96.4,"crime":"G.L.A."},{"yr_1990":59088,"yr_1993":48256,"yr_1998":22666,"yr_2001":16803,"yr_2013":11860,"pct_change_13vs01":-29.42,"pct_change_13vs98":-47.67,"pct_change_13vs93":-75.42,"pct_change_13vs90":-79.93,"crime":"TOTAL"}]}